sjmm_util/__init__.py
sjmm_util/config.py
sjmm_util/general_utils.py
sjmm_util/line_utils.py
sjmm_util/scuba2_utils.py
sjmm_util/sjmdefaults.mplstyle
sjmm_util-0.2.2.dist-info/licenses/LICENSE
sjmm_util-0.2.2.dist-info/METADATA
sjmm_util-0.2.2.dist-info/WHEEL
sjmm_util-0.2.2.dist-info/top_level.txt
sjmm_util-0.2.2.dist-info/RECORD
