Metadata-Version: 2.4
Name: sjmm_util
Version: 0.2.2
License-File: LICENSE
Requires-Dist: numpy
Requires-Dist: pandas
Requires-Dist: matplotlib
Requires-Dist: astropy
Requires-Dist: reproject
Requires-Dist: scipy
Requires-Dist: scikit-image
Dynamic: license-file
